LICENSE
LICENSE.txt
README.rst
setup.cfg
setup.py
dream_river/ML.py
dream_river/__init__.py
dream_river/convertools.py
dream_river/geobox.py
dream_river/indices.py
dream_river/plotimg.py
dream_river.egg-info/PKG-INFO
dream_river.egg-info/SOURCES.txt
dream_river.egg-info/dependency_links.txt
dream_river.egg-info/requires.txt
dream_river.egg-info/top_level.txt