Metadata-Version: 2.1
Name: dream-river
Version: 0.0.6
Summary: This is a library contained rice detection tools and other geospatial tools for jupyter environment on sphere.gistda.or.th in part of Data Cube
Home-page: https://github.com/Pathakorn40/rice-detection
Author: Pathakorn Usaha
Author-email: dreamusaha@gmail.com
License: MIT
Download-URL: https://pypi.org/project/dream_river/
Keywords: geography,geospatiol,gis,rice detection
Platform: UNKNOWN
Classifier: Development Status :: 3 - Alpha
Classifier: Intended Audience :: Science/Research
Classifier: Topic :: Software Development :: Build Tools
Classifier: License :: OSI Approved :: MIT License
Classifier: Programming Language :: Python :: 3
Classifier: Programming Language :: Python :: 3.4
Classifier: Programming Language :: Python :: 3.5
Classifier: Programming Language :: Python :: 3.6
Classifier: Programming Language :: Python :: 3.7
Classifier: Programming Language :: Python :: 3.8
Classifier: Programming Language :: Python :: 3.9
License-File: LICENSE
License-File: LICENSE.txt
